protocol_verwerker/__init__.py
protocol_verwerker/__main__.py
protocol_verwerker/frequentietabel_generator.py
protocol_verwerker/sequentietabel_generator.py
protocol_verwerker-0.0.3.dist-info/LICENSE
protocol_verwerker-0.0.3.dist-info/METADATA
protocol_verwerker-0.0.3.dist-info/WHEEL
protocol_verwerker-0.0.3.dist-info/entry_points.txt
protocol_verwerker-0.0.3.dist-info/top_level.txt
protocol_verwerker-0.0.3.dist-info/RECORD
