Metadata-Version: 2.1
Name: protocol-verwerker
Version: 0.0.3
Summary: Een python script om een sequentietabel te genereren uit een protocol.
Classifier: Programming Language :: Python :: 3
Classifier: License :: OSI Approved :: MIT License
Classifier: Operating System :: OS Independent
License-File: LICENSE
Requires-Dist: pandas
